example.v
`define s0 5'd0
`define s1 5'd1
`define s2 5'd2
`define s3 5'd3
`define s4 5'd4
`define s5 5'd5
`define s6 5'd6
`define s7 5'd7
`define s8 5'd8
`define s9 5'd9
`define s10 5'd10
`define s11 5'd11
`define s12 5'd12
`define s13 5'd13
`define s14 5'd14
`define s15 5'd15
`define s16 5'd16
`define s17 5'd17
`define s18 5'd18
`define s19 5'd19
`define s20 5'd20
`define s21 5'd21
`define s22 5'd22
`define s23 5'd23
`define s24 5'd24
`define s25 5'd25
`define s26 5'd26



module example (ID, clock, state, next_state,clear, maxout,a1,a2,a3,b1,b2,b3,c1,c2,c3,d1,d2,d3,ss1,ss2,ss3,ss4);
    output reg [11:0]ID;
    output reg [5:0]state;
    output reg [5:0]next_state;
    output reg [2:0]maxout;

    // input clear,clock,a1,a2,a3,b1,b2,b3,c1,c2,c3,d1,d2,d3,ss1,ss2,ss3,ss4;
    // wire[2:0] max_out;
    // find_max fm_inst(a1,a2,a3,b1,b2,b3,c1,c2,c3,d1,d2,d3,max_out);

   initial begin
    state = s0;
    next_state = s0;
    ID = 12'b100100100100;
   end

   always @(posedge clock) 
    next_state = state;
   

   always @(state) begin
     case (state)
       `s0 : begin
              ID = 12'b100100100100;
             end
       `s1 : begin
               ID = 12'b100100100100;
             end 
       `s2 : begin
               ID = 12'b100100100100;
             end            
       `s3 : begin
               ID = 12'b100100100100;
             end 
       `s4 : begin
               ID = 12'b100100100100;
             end     
       `s5 : begin
               ID = 12'b100100100100;
             end
       `s6 : begin
               ID = 12'b001100100100;
             end
       `s7 : begin
               ID = 12'b001100100100;
             end
       `s8 : begin
               ID = 12'b001100100100;
             end 
       `s9 : begin
               ID = 12'b010100100100;
             end
       `s10 : begin
               ID = 12'b100001100100;
             end
       `s11 : begin
               ID = 12'b100001100100;
             end
       `s12 : begin
               ID = 12'b100001100100;
             end
       `s13 : begin
               ID = 12'b100010100100;
             end
       `s14 : begin
               ID = 12'b100100001100;
             end
       `s15 : begin
               ID = 12'b100100001100;
             end
       `s16 : begin
               ID = 12'b100100001100;
             end
       `s17 : begin
               ID = 12'b100100010100;
             end
       `s18 : begin
               ID = 12'b100100100001;
             end
       `s19 : begin
               ID = 12'b100100100001;
             end
       `s20 : begin
               ID = 12'b100100100001;
             end
       `s21 : begin
               ID = 12'b100100100010;
             end
       `s22 : begin
               ID = 12'b100100100100;
             end
       `s23 : begin
               ID = 12'b001100100100;
             end
       `s24 : begin
               ID = 12'b100001100100;
             end
       `s25 : begin
               ID = 12'b100100001100;
             end
       `s26 : begin
               ID = 12'b100100100001;
             end     
        default: ID = 12'b100100100100;
     endcase
   end
   
  always @(state or clear or a1 or a2 or a3 or b1 or b2 or b3 or c1 or c2 or c3 or d1 or d2 or d3 or ss1 or ss2 or ss3 or ss4)
   begin
    if(clear)
     next_state = `s0;

    else
    begin
      case (state)
       `s0 :begin
                if(ss1 || ss2 || ss3 || ss4)
                  next_state = `s22;

                if (a1 || b1 || c1 || d1) 
                  next_state = `s1;
         
                else
                  next_state = `s0;
            end

       `s1 : begin
                
                find_max(a1,a2,a3,b1,b2,b3,c1,c2,c3,d1,d2,d3,maxout);
               
                case (maxout)
                   1: next_state = `s2;
                   2: next_state = `s3;
                   3: next_state = `s4;
                   4: next_state = `s5; 
         
                  default: next_state = `s1;  
                endcase
              end

       `s2: begin
                if(a1 && a2 && a3)
                  next_state = `s8;

                else if(a1 && a2 && ~a3)
                  next_state = `s7;

                 else
                  next_state = `s6;
            end

       `s3: begin
                if(b1 && b2 && b3)
                  next_state = `s12;

                else if(b1 && b2 && ~b3)
                  next_state = `s11;

                else
                  next_state = `s10;
            end

       `s4: begin
                if(c1 && c2 && c3)
                  next_state = `s16;

                else if(c1 && c2 && ~c3)
                  next_state = `s15;

                else
                  next_state = `s14;
            end

       `s5: begin
                if(d1 && d2 && d3)
                  next_state = `s20;

                else if(d1 && d2 && ~d3)
                  next_state = `s19;

                else
                  next_state = `s18;
            end

       `s6: begin
                 if(ss2||ss3||ss4||~a1||b2||c2||d2)
                  next_state = `s9;

                 else
                  next_state = `s6;
            end

       `s7: begin
                if((~a1 && ~a2)||b3||c3||d3||ss2||ss3||ss4)
                  next_state = `s9;

                if(a1 && a2)
                  next_state = `s7;

                if(~a2 && a1)
                  next_state = `s6;
            end

       `s8: begin
                  if((~a1 && ~a2 && ~a3)||ss2||ss3||ss4)
                    next_state = `s9;

                  if(a1 && a2 && a3)
                    next_state = `s8;

                  if(~a3 && a2 && a1)
                    next_state = `s7;

                  if(~a3 && ~a2 && a1)
                    next_state = `s6;
            end

       `s9: begin
                 next_state = `s0;
       end

       `s10: begin
                 if(ss1||ss3||ss4||~b1||a2||c2||d2)
                    next_state = `s13;

                 else
                    next_state = `s10;
             end

       `s11: begin
                 if((~b1 && ~b2)||a3||c3||d3||ss1||ss3||ss4)
                    next_state = `s13;

                 if(b1 && b2)
                    next_state = `s11;

                 if(~b2 && b1)
                    next_state = `s10;
              end

       `s12: begin
                 if((~b1 && ~b2 && ~b3)||ss1||ss3||ss4)
                    next_state = `s13;

                 if(b1 && b2 && b3)
                    next_state = `s12;

                 if(~b3 && b2 && b1)
                    next_state = `s11;

                 if(~b3 && ~b2 && b1)
                    next_state = `s10;
             end

       `s13: begin
                 next_state = `s0;
       end

       `s14: begin
                if(ss2||ss1||ss4||~c1||b2||a2||d2)
                   next_state = `s17;

                else
                   next_state = `s14;
       end

       `s15: begin
                if((~c1 && ~c2)||b3||a3||d3||ss2||ss1||ss4)
                   next_state = `s17;

                if(c1 && c2)
                   next_state = `s15;

                if(~c2 && c1)
                   next_state = `s14;
             end

       `s16: begin
                if((~c1 && ~c2 && ~c3)||ss2||ss1||ss4)
                  next_state = `s17;

                if(c1 && c2 && c3)
                  next_state = `s16;

                if(~c3 && c2 && c1)
                  next_state = `s15;

                if(~c3 && ~c2 && c1)
                  next_state = `s14;
            end

       `s17: begin
                next_state = `s0;
             end

       `s18: begin
                if(ss2||ss3||ss1||~d1||b2||c2||a2)
                 next_state = `s21;

               else
                 next_state = `s18;
             end

       `s19: begin
               if((~d1 && ~d2)||b3||c3||a3||ss2||ss3||ss1)
                next_state = `s21;

               if(d1 && d2)
                 next_state = `s19;

              if(~d2 && d1)
                  next_state = `s18;
             end

       `s20: begin
               if((~d1 && ~d2 && ~d3)||ss2||ss3||ss1)
                    next_state = `s21;

               if(d1 && d2 && d3)
                 next_state = `s20;

               if(~d3 && d2 && d1)
                 next_state = `s19;

               if(~d3 && ~d2 && d1)
                  next_state = `s18;
             end

       `s21: begin
               next_state = `s0;
             end

       `s22: begin
              if(ss1)
                next_state = `s23;
              else if(ss2)
                next_state = `s24;
              else if(ss3)
                next_state = `s25;
              else if(ss4)
                next_state = `s26;
             end

       `s23: begin
              if(ss1)
                next_state = `s23;
              else
                next_state = `s9;
             end

       `s24: begin
              if(ss2)
               next_state = `s24;
              else
               next_state = `s13;
             end

       `s25: begin
              if(ss3)
                next_state = `s25;
              else
                next_state = `s17;
             end

       `s26: begin
               if(ss4)
                 next_state = `s26;
               else
                 next_state = `s21;
             end
        default: next_state = `s0;
      endcase
     end
   end


  //  task find_max;
  //  input a1,a2,a3,b1,b2,b3,c1,c2,c3,d1,d2,d3;
  //  output [2:0] max;
  //  reg [2:0] a,b,c,d;
  //  a = {a1,a2,a3};
  //  b = {b1,b2,b3};
  //  c = {c1,c2,c3};
  //  d = {d1,d2,d3};
  // begin
    
  
  //  if(a>=b)
  //  begin
  //   if(a>=c)
  //   begin
  //     if(a>=d)
  //     max = 1;

  //     else
  //     max = 4;
  //   end
  //   else
  //   begin
  //     if(c>=d)
  //     max = 3;

  //     else
  //     max =4;
  //   end
  //  end 

  //  else
  //  begin
  //   if(b>=c)
  //   begin
  //     if(b>=d)
  //     max =2;

  //     else
  //     max =4;
  //   end
  //   else
  //   begin
  //     if(c>=d)
  //     max = 3;
  //     else
  //     max = 4;
  //   end
  //  end
  //  end
  //  endtask
  task find_max;
   input a1, a2, a3, b1, b2, b3, c1, c2, c3, d1, d2, d3;
   output reg [2:0] max; // Declare max as a reg since it's assigned inside the task

   reg [2:0] a, b, c, d; // Declare a, b, c, d inside the task

   begin
      a = {a1, a2, a3};
      b = {b1, b2, b3};
      c = {c1, c2, c3};
      d = {d1, d2, d3};

      if (a >= b) begin
         if (a >= c) begin
            if (a >= d)
               max = 1; // 1 in binary
            else
               max = 4; // 4 in binary
         end else begin
            if (c >= d)
               max = 3; // 3 in binary
            else
               max = 4; // 4 in binary
         end
      end else begin
         if (b >= c) begin
            if (b >= d)
               max = 2; // 2 in binary
            else
               max = 4; // 4 in binary
         end else begin
            if (c >= d)
               max = 3; // 3 in binary
            else
               max = 4; // 4 in binary
         end
      end
   end
endtask



endmodule

example_tb.v
`include "example.v"
`timescale 1ns / 1ps

module example_tb;
  
  // Inputs
  reg clock;
  reg clear;
  reg a1, a2, a3;
  reg b1, b2, b3;
  reg c1, c2, c3;
  reg d1, d2, d3;
  reg ss1, ss2, ss3, ss4;
  integer i;
  // Outputs
  wire [11:0] ID;
  wire [5:0] state;
  wire [5:0] next_state;
  wire [2:0] maxout;
  
  // Instantiate the Unit Under Test (UUT)
  example uut (
    .ID(ID), 
    .clock(clock), 
    .state(state), 
    .next_state(next_state), 
    .clear(clear), 
    .maxout(maxout), 
    .a1(a1), .a2(a2), .a3(a3),
    .b1(b1), .b2(b2), .b3(b3),
    .c1(c1), .c2(c2), .c3(c3),
    .d1(d1), .d2(d2), .d3(d3),
    .ss1(ss1), .ss2(ss2), .ss3(ss3), .ss4(ss4)
  );
  
  // Clock generation
  initial begin
    clock = 0;
    forever #1 clock = ~clock; // Toggle clock every 5 time units
  end
  
  // Test procedure
  initial begin
    // Initial setup and first display after 5 time units
    // #5 
    // $display("Time: %0d | a1: %b | a2: %b | a3: %b | b1: %b | b2: %b | b3: %b | c1: %b | c2: %b | c3: %b | d1: %b | d2: %b | d3: %b | ss1: %b | ss2: %b | ss3: %b | ss4: %b | state: %0d | ID: %b",
    //          $time, a1, a2, a3, b1, b2, b3, c1, c2, c3, d1, d2, d3, ss1, ss2, ss3, ss4, state, ID);
    
    // Change inputs and display after 10 time units
    a1=1'b1; a2=1'b1; a3=1'b1;
    b1=1'b1; b2=1'b0; b3=1'b0;
    c1=1'b1; c2=1'b0; c3=1'b0;
    d1=1'b1; d2=1'b1; d3=1'b0;
    ss1=1'b0; ss2=1'b0; ss3=1'b0; ss4=1'b0;
    
    
    for(i=0; i<10; i= i+1)
       begin
        #1
        $display("Time: %0d | a1: %b | a2: %b | a3: %b | b1: %b | b2: %b | b3: %b | c1: %b | c2: %b | c3: %b | d1: %b | d2: %b | d3: %b | ss1: %b | ss2: %b | ss3: %b | ss4: %b | next_state: %0d | state: %0d | ID: %b",
             $time, a1, a2, a3, b1, b2, b3, c1, c2, c3, d1, d2, d3, ss1, ss2, ss3, ss4, next_state, state, ID);

       end
    // Set ss3 high and display after 5 more time units
    a1=1'b0; a2=1'b0; a3=1'b0;
    b1=1'b0; b2=1'b0; b3=1'b0;
    c1=1'b0; c2=1'b0; c3=1'b0;
    d1=1'b0; d2=1'b0; d3=1'b0;
    ss1=1'b0; ss2=1'b0; ss3=1'b1; ss4=1'b0;
    
        
    for(i=0; i<10; i= i+1)
       begin
        #1
        $display("Time: %0d | a1: %b | a2: %b | a3: %b | b1: %b | b2: %b | b3: %b | c1: %b | c2: %b | c3: %b | d1: %b | d2: %b | d3: %b | ss1: %b | ss2: %b | ss3: %b | ss4: %b | next_state: %0d | state: %0d | ID: %b",
             $time, a1, a2, a3, b1, b2, b3, c1, c2, c3, d1, d2, d3, ss1, ss2, ss3, ss4, next_state, state, ID);

       end
    // // Uncommented code and further changes
    
    ss3 = 1'b0; // Set ss3 low
    b1 = 1'b1;  // Set b1 high
    b2 = 1'b1;  // Set b2 high
    
      for(i=0; i<15; i= i+1)
       begin
        #1
        $display("Time: %0d | a1: %b | a2: %b | a3: %b | b1: %b | b2: %b | b3: %b | c1: %b | c2: %b | c3: %b | d1: %b | d2: %b | d3: %b | ss1: %b | ss2: %b | ss3: %b | ss4: %b | next_state: %0d | state: %0d | ID: %b",
             $time, a1, a2, a3, b1, b2, b3, c1, c2, c3, d1, d2, d3, ss1, ss2, ss3, ss4, next_state, state, ID);

       end
       // Set ss3 high and display after 5 more time units
    a1=1'b0; a2=1'b0; a3=1'b0;
    b1=1'b0; b2=1'b0; b3=1'b0;
    c1=1'b0; c2=1'b0; c3=1'b0;
    d1=1'b0; d2=1'b0; d3=1'b0;
    ss1=1'b0; ss2=1'b0; ss3=1'b0; ss4=1'b0;
    
        
    for(i=0; i<10; i= i+1)
       begin
        #1
        $display("Time: %0d | a1: %b | a2: %b | a3: %b | b1: %b | b2: %b | b3: %b | c1: %b | c2: %b | c3: %b | d1: %b | d2: %b | d3: %b | ss1: %b | ss2: %b | ss3: %b | ss4: %b | next_state: %0d | state: %0d | ID: %b",
             $time, a1, a2, a3, b1, b2, b3, c1, c2, c3, d1, d2, d3, ss1, ss2, ss3, ss4, next_state, state, ID);

       end

    #5
    $finish;
end

  
endmodule

example.vcd
$date
	Thu Oct 17 18:27:29 2024
$end
$version
	Icarus Verilog
$end
$timescale
	1ps
$end
$scope module example_tb $end
$var wire 12 ! ID [11:0] $end
$var wire 3 " maxout [2:0] $end
$var wire 6 # next_state [5:0] $end
$var wire 6 $ state [5:0] $end
$var reg 1 % a1 $end
$var reg 1 & a2 $end
$var reg 1 ' a3 $end
$var reg 1 ( b1 $end
$var reg 1 ) b2 $end
$var reg 1 * b3 $end
$var reg 1 + c1 $end
$var reg 1 , c2 $end
$var reg 1 - c3 $end
$var reg 1 . clear $end
$var reg 1 / clock $end
$var reg 1 0 d1 $end
$var reg 1 1 d2 $end
$var reg 1 2 d3 $end
$var integer 32 3 i [31:0] $end
$var reg 1 4 ss1 $end
$var reg 1 5 ss2 $end
$var reg 1 6 ss3 $end
$var reg 1 7 ss4 $end
$scope module uut $end
$var wire 1 8 a1 $end
$var wire 1 9 a2 $end
$var wire 1 : a3 $end
$var wire 1 ; b1 $end
$var wire 1 < b2 $end
$var wire 1 = b3 $end
$var wire 1 > c1 $end
$var wire 1 ? c2 $end
$var wire 1 @ c3 $end
$var wire 1 A clear $end
$var wire 1 B clock $end
$var wire 1 C d1 $end
$var wire 1 D d2 $end
$var wire 1 E d3 $end
$var wire 1 F ss1 $end
$var wire 1 G ss2 $end
$var wire 1 H ss3 $end
$var wire 1 I ss4 $end
$var reg 12 J ID [11:0] $end
$var reg 3 K maxout [2:0] $end
$var reg 6 L next_state [5:0] $end
$var reg 6 M state [5:0] $end
$scope task find_max $end
$var reg 3 N a [2:0] $end
$var reg 1 O a1 $end
$var reg 1 P a2 $end
$var reg 1 Q a3 $end
$var reg 3 R b [2:0] $end
$var reg 1 S b1 $end
$var reg 1 T b2 $end
$var reg 1 U b3 $end
$var reg 3 V c [2:0] $end
$var reg 1 W c1 $end
$var reg 1 X c2 $end
$var reg 1 Y c3 $end
$var reg 3 Z d [2:0] $end
$var reg 1 [ d1 $end
$var reg 1 \ d2 $end
$var reg 1 ] d3 $end
$var reg 3 ^ max [2:0] $end
$upscope $end
$upscope $end
$upscope $end
$enddefinitions $end
#0
$dumpvars
bx ^
x]
x\
x[
bx Z
xY
xX
xW
bx V
xU
xT
xS
bx R
xQ
xP
xO
bx N
b0 M
b1 L
bx K
b100100100100 J
0I
0H
0G
0F
0E
1D
1C
0B
xA
0@
0?
1>
0=
0<
1;
1:
19
18
07
06
05
04
b0 3
02
11
10
0/
x.
0-
0,
1+
0*
0)
1(
1'
1&
1%
b0 $
b1 #
bx "
b100100100100 !
$end
#500
b10 L
b10 #
b1 K
b1 "
b1 ^
b110 Z
b100 V
b100 R
b111 N
0]
1\
1[
0Y
0X
1W
0U
0T
1S
1Q
1P
1O
b1 M
b1 $
1/
1B
#1000
0/
0B
b1 3
#1500
b1000 L
b1000 #
b10 M
b10 $
1/
1B
#2000
0/
0B
b10 3
#2500
b1100100100 J
b1100100100 !
b1000 M
b1000 $
1/
1B
#3000
0/
0B
b11 3
#3500
1/
1B
#4000
0/
0B
b100 3
#4500
1/
1B
#5000
0/
0B
b101 3
#5500
1/
1B
#6000
0/
0B
b110 3
#6500
1/
1B
#7000
0/
0B
b111 3
#7500
1/
1B
#8000
0/
0B
b1000 3
#8500
1/
1B
#9000
0/
0B
b1001 3
#9500
1/
1B
#10000
b1001 L
b1001 #
0/
0B
16
1H
01
0D
00
0C
0+
0>
0(
0;
0'
0:
0&
09
0%
08
b0 3
#10500
b0 L
b0 #
b10100100100 J
b10100100100 !
b1001 M
b1001 $
1/
1B
#11000
0/
0B
b1 3
#11500
b10110 L
b10110 #
b100100100100 J
b100100100100 !
b0 M
b0 $
1/
1B
#12000
0/
0B
b10 3
#12500
b11001 L
b11001 #
b10110 M
b10110 $
1/
1B
#13000
0/
0B
b11 3
#13500
b100100001100 J
b100100001100 !
b11001 M
b11001 $
1/
1B
#14000
0/
0B
b100 3
#14500
1/
1B
#15000
0/
0B
b101 3
#15500
1/
1B
#16000
0/
0B
b110 3
#16500
1/
1B
#17000
0/
0B
b111 3
#17500
1/
1B
#18000
0/
0B
b1000 3
#18500
1/
1B
#19000
0/
0B
b1001 3
#19500
1/
1B
#20000
b10001 L
b10001 #
0/
0B
1)
1<
1(
1;
06
0H
b0 3
#20500
b0 L
b0 #
b100100010100 J
b100100010100 !
b10001 M
b10001 $
1/
1B
#21000
0/
0B
b1 3
#21500
b1 L
b1 #
b100100100100 J
b100100100100 !
b0 M
b0 $
1/
1B
#22000
0/
0B
b10 3
#22500
b11 L
b11 #
b10 K
b10 "
b10 ^
b0 Z
b0 V
b110 R
b0 N
0\
0[
0W
1T
0Q
0P
0O
b1 M
b1 $
1/
1B
#23000
0/
0B
b11 3
#23500
b1011 L
b1011 #
b11 M
b11 $
1/
1B
#24000
0/
0B
b100 3
#24500
b100001100100 J
b100001100100 !
b1011 M
b1011 $
1/
1B
#25000
0/
0B
b101 3
#25500
1/
1B
#26000
0/
0B
b110 3
#26500
1/
1B
#27000
0/
0B
b111 3
#27500
1/
1B
#28000
0/
0B
b1000 3
#28500
1/
1B
#29000
0/
0B
b1001 3
#29500
1/
1B
#30000
0/
0B
b1010 3
#30500
1/
1B
#31000
0/
0B
b1011 3
#31500
1/
1B
#32000
0/
0B
b1100 3
#32500
1/
1B
#33000
0/
0B
b1101 3
#33500
1/
1B
#34000
0/
0B
b1110 3
#34500
1/
1B
#35000
b1101 L
b1101 #
0/
0B
0)
0<
0(
0;
b0 3
#35500
b0 L
b0 #
b100010100100 J
b100010100100 !
b1101 M
b1101 $
1/
1B
#36000
0/
0B
b1 3
#36500
b100100100100 J
b100100100100 !
b0 M
b0 $
1/
1B
#37000
0/
0B
b10 3
#37500
1/
1B
#38000
0/
0B
b11 3
#38500
1/
1B
#39000
0/
0B
b100 3
#39500
1/
1B
#40000
0/
0B
b101 3
#40500
1/
1B
#41000
0/
0B
b110 3
#41500
1/
1B
#42000
0/
0B
b111 3
#42500
1/
1B
#43000
0/
0B
b1000 3
#43500
1/
1B
#44000
0/
0B
b1001 3
#44500
1/
1B
#45000
0/
0B
b1010 3
